[{"id": 51928, "name": "The Lord of the Rings: The Return of the King"}, {"id": 51929, "name": "The Lord of the Rings: The Two Towers"}, {"id": 51930, "name": "The Lord of the Rings: The Fellowship of the Ring"}, {"id": 51590, "name": "Once Were Warriors"}, {"id": 25320, "name": "Boy"}, {"id": 172537, "name": "What We Do in the Shadows"}, {"id": 307239, "name": "Hunt for the Wilderpeople"}, {"id": 200619, "name": "The Dark Horse"}, {"id": 1146273, "name": "Tinā"}, {"id": 51389, "name": "Braindead"}, {"id": 706593, "name": "Cousins"}, {"id": 444600, "name": "Jojo Rabbit"}, {"id": 51158, "name": "Whale Rider"}, {"id": 50032, "name": "An Angel at My Table"}, {"id": 40860, "name": "District 9"}, {"id": 44860, "name": "Merry Christmas, Mr. Lawrence"}, {"id": 51169, "name": "Heavenly Creatures"}, {"id": 22943, "name": "Utu"}, {"id": 45841, "name": "Out of the Blue"}, {"id": 51145, "name": "In My Father's Den"}, {"id": 896730, "name": "The Raid"}, {"id": 1112713, "name": "We Were Dangerous"}, {"id": 641594, "name": "Rurangi"}, {"id": 40915, "name": "The Adventures of Tintin"}, {"id": 30418, "name": "Forgotten Silver"}, {"id": 46473, "name": "The Quiet Earth"}, {"id": 395091, "name": "Waru"}, {"id": 34183, "name": "Vigil"}, {"id": 352870, "name": "McLaren"}, {"id": 40574, "name": "Dean Spanley"}, {"id": 177136, "name": "Housebound"}, {"id": 527841, "name": "The Power of the Dog"}, {"id": 678065, "name": "The Justice of Bunny King"}, {"id": 933547, "name": "Uproar"}, {"id": 46722, "name": "The World's Fastest Indian"}, {"id": 974570, "name": "Red, White & Brass"}, {"id": 29893, "name": "Smash Palace"}, {"id": 157807, "name": "Slow West"}, {"id": 43973, "name": "Sione's Wedding"}, {"id": 38917, "name": "Footrot Flats: The Dog's Tale"}, {"id": 16525, "name": "The Hobbit: An Unexpected Journey"}, {"id": 666321, "name": "The Emigrants"}, {"id": 47622, "name": "Eagle vs Shark"}, {"id": 62285, "name": "Hercules in the Underworld"}, {"id": 27066, "name": "Hercules and the Amazon Women"}, {"id": 634949, "name": "Coming Home in the Dark"}, {"id": 62297, "name": "Hercules and the Circle of Fire"}, {"id": 553446, "name": "Savage"}, {"id": 8983, "name": "The Hobbit: The Desolation of Smaug"}, {"id": 62293, "name": "Hercules and the Lost Kingdom"}]