[
  {
    "id": 51523,
    "name": "City of God"
  },
  {
    "id": 51458,
    "name": "Central Station"
  },
  {
    "id": 901671,
    "name": "I'm Still Here"
  },
  {
    "id": 111148,
    "name": "Rio, Northern Zone"
  },
  {
    "id": 36112,
    "name": "The Secret in Their Eyes"
  },
  {
    "id": 266074,
    "name": "Embrace of the Serpent"
  },
  {
    "id": 6578,
    "name": "The Given Word"
  },
  {
    "id": 22918,
    "name": "Pixote"
  },
  {
    "id": 24788,
    "name": "A Dog's Will"
  },
  {
    "id": 237642,
    "name": "The Second Mother"
  },
  {
    "id": 47251,
    "name": "Fitzcarraldo"
  },
  {
    "id": 188497,
    "name": "Wild Tales"
  },
  {
    "id": 429571,
    "name": "The Wolf House"
  },
  {
    "id": 47723,
    "name": "Carandiru"
  },
  {
    "id": 40595,
    "name": "Nine Queens"
  },
  {
    "id": 89051,
    "name": "Extraordinary Stories"
  },
  {
    "id": 145451,
    "name": "They Don't Wear Black Tie"
  },
  {
    "id": 14634,
    "name": "Monica's Gang in an Adventure in Time"
  },
  {
    "id": 477325,
    "name": "Invisible Life"
  },
  {
    "id": 21721,
    "name": "Time for Revenge"
  },
  {
    "id": 63158,
    "name": "Sidewalls"
  },
  {
    "id": 441151,
    "name": "Eternity"
  },
  {
    "id": 181870,
    "name": "The Boy and the Wind"
  },
  {
    "id": 254187,
    "name": "Compasso de Espera"
  },
  {
    "id": 12806,
    "name": "La boca del lobo"
  },
  {
    "id": 139935,
    "name": "The Guns"
  },
  {
    "id": 537,
    "name": "Basic Sanitation, the Movie"
  },
  {
    "id": 123659,
    "name": "Movie Dementia"
  },
  {
    "id": 61954,
    "name": "São Paulo, Incorporated"
  },
  {
    "id": 13540,
    "name": "Lisbela and the Prisoner"
  },
  {
    "id": 6435,
    "name": "To the Left of the Father"
  },
  {
    "id": 110671,
    "name": "Rio, 100 Degrees F°"
  },
  {
    "id": 132653,
    "name": "Buccaneer Soul"
  },
  {
    "id": 54348,
    "name": "Estômago: A Gastronomic Story"
  },
  {
    "id": 177223,
    "name": "Saint Bernard"
  },
  {
    "id": 93087,
    "name": "Case of the Naves Brothers"
  },
  {
    "id": 638659,
    "name": "Trenque Lauquen"
  },
  {
    "id": 8384,
    "name": "Foreign Land"
  },
  {
    "id": 48042,
    "name": "Elite Squad"
  },
  {
    "id": 171254,
    "name": "Garden of War"
  },
  {
    "id": 637929,
    "name": "Argentina 1985"
  },
  {
    "id": 33009,
    "name": "The Official Story"
  },
  {
    "id": 64774,
    "name": "On Probation"
  },
  {
    "id": 137650,
    "name": "My Sweet Orange Tree"
  },
  {
    "id": 312510,
    "name": "Aquarius"
  },
  {
    "id": 157902,
    "name": "Boy & the World"
  },
  {
    "id": 12049,
    "name": "Brainstorm"
  },
  {
    "id": 21720,
    "name": "Martin (Hache)"
  },
  {
    "id": 140052,
    "name": "The Woman Who Invented Love"
  },
  {
    "id": 904947,
    "name": "Willaq Pirqa, the Cinema of My Village"
  },
  {
    "id": 24163,
    "name": "The Man Who Copied"
  },
  {
    "id": 107097,
    "name": "Love Torn in a Dream"
  },
  {
    "id": 134882,
    "name": "No Way, Spider"
  },
  {
    "id": 182170,
    "name": "The Deceased"
  },
  {
    "id": 17503,
    "name": "Elite Squad: The Enemy Within"
  },
  {
    "id": 39130,
    "name": "Red Ink"
  },
  {
    "id": 1706,
    "name": "Days of Santiago"
  },
  {
    "id": 370918,
    "name": "Birds of Passage"
  },
  {
    "id": 72977,
    "name": "Assault on the Pay Train"
  },
  {
    "id": 997183,
    "name": "Simón"
  },
  {
    "id": 43711,
    "name": "Waiting for the Hearse"
  },
  {
    "id": 133978,
    "name": "The Bitter Stems"
  },
  {
    "id": 72903,
    "name": "The Amulet of Ogum"
  },
  {
    "id": 118498,
    "name": "Reflections of a Blender"
  },
  {
    "id": 46642,
    "name": "The Strategy of the Snail"
  },
  {
    "id": 50889,
    "name": "The Motorcycle Diaries"
  },
  {
    "id": 18595,
    "name": "The South"
  },
  {
    "id": 378601,
    "name": "Bacurau"
  },
  {
    "id": 122888,
    "name": "The Wrung-Out Man"
  },
  {
    "id": 30283,
    "name": "A Place in the World"
  },
  {
    "id": 134880,
    "name": "The Red Light Bandit"
  },
  {
    "id": 10124,
    "name": "Entranced Earth"
  },
  {
    "id": 28197,
    "name": "Behind the Sun"
  },
  {
    "id": 429646,
    "name": "Retablo"
  },
  {
    "id": 252473,
    "name": "Endless Poetry"
  },
  {
    "id": 362368,
    "name": "Bingo: The King of the Mornings"
  },
  {
    "id": 595544,
    "name": "Prayers for the Stolen"
  },
  {
    "id": 3922,
    "name": "Ai que Vida!"
  },
  {
    "id": 167044,
    "name": "The Way He Looks"
  },
  {
    "id": 7845,
    "name": "La Ciénaga"
  },
  {
    "id": 138490,
    "name": "Copacabana Mon Amour"
  },
  {
    "id": 39625,
    "name": "Son of the Bride"
  },
  {
    "id": 819858,
    "name": "Mars One"
  },
  {
    "id": 175794,
    "name": "All the Women in the World"
  },
  {
    "id": 1042337,
    "name": "Yana-Wara"
  },
  {
    "id": 140357,
    "name": "Men and Women"
  },
  {
    "id": 133008,
    "name": "The Margin"
  },
  {
    "id": 152108,
    "name": "A Wolf at the Door"
  },
  {
    "id": 133132,
    "name": "The Kiss"
  },
  {
    "id": 183424,
    "name": "The Devil Queen"
  },
  {
    "id": 63269,
    "name": "The Age of the Earth"
  },
  {
    "id": 296346,
    "name": "Nise: The Heart of Madness"
  },
  {
    "id": 105583,
    "name": "The Dance of Reality"
  },
  {
    "id": 124817,
    "name": "Fake Blonde"
  },
  {
    "id": 138489,
    "name": "The Woman of Everyone"
  },
  {
    "id": 522126,
    "name": "Sertânia"
  },
  {
    "id": 16761,
    "name": "Man Facing Southeast"
  },
  {
    "id": 25302,
    "name": "The Wind Journeys"
  },
  {
    "id": 213376,
    "name": "The History of Eternity"
  },
  {
    "id": 61701,
    "name": "Love Me Forever or Never"
  },
  {
    "id": 56641,
    "name": "Jackal of Nahueltoro"
  },
  {
    "id": 127305,
    "name": "Bang Bang"
  },
  {
    "id": 79971,
    "name": "The Rose Seller"
  },
  {
    "id": 18377,
    "name": "Madame Satã"
  },
  {
    "id": 852109,
    "name": "Our Dream"
  },
  {
    "id": 24539,
    "name": "Black Orpheus"
  },
  {
    "id": 132636,
    "name": "The Sign of Chaos"
  },
  {
    "id": 3758,
    "name": "25 Watts"
  },
  {
    "id": 160163,
    "name": "Tattoo"
  },
  {
    "id": 94164,
    "name": "The Priest and the Girl"
  },
  {
    "id": 367390,
    "name": "Araby"
  },
  {
    "id": 351390,
    "name": "The Cambridge Squatter"
  },
  {
    "id": 44813,
    "name": "Machuca"
  },
  {
    "id": 444346,
    "name": "A Twelve-Year Night"
  },
  {
    "id": 401395,
    "name": "Coffee With Cinnamon"
  },
  {
    "id": 27408,
    "name": "31 Minutos, la película"
  },
  {
    "id": 126452,
    "name": "The Murdered House"
  },
  {
    "id": 121160,
    "name": "The Empire of Desire"
  },
  {
    "id": 61965,
    "name": "Antonio das Mortes"
  },
  {
    "id": 139972,
    "name": "Porto das Caixas"
  },
  {
    "id": 60986,
    "name": "Durval Discos"
  },
  {
    "id": 413058,
    "name": "The Asphalt Kiss"
  },
  {
    "id": 407054,
    "name": "The Seamstress"
  },
  {
    "id": 73864,
    "name": "I Travel Because I Have to, I Come Back Because I Love You"
  },
  {
    "id": 88499,
    "name": "No"
  },
  {
    "id": 213345,
    "name": "The Act in Question"
  },
  {
    "id": 26694,
    "name": "Ó Paí, Ó: Look at This"
  },
  {
    "id": 264105,
    "name": "Beyond Oblivion"
  },
  {
    "id": 31644,
    "name": "If I Should Die Before I Wake"
  },
  {
    "id": 587860,
    "name": "Monica and Friends: Lessons"
  },
  {
    "id": 762717,
    "name": "The Kings of the World"
  },
  {
    "id": 78923,
    "name": "Love for Sale"
  },
  {
    "id": 14434,
    "name": "Intimate Stories"
  },
  {
    "id": 140242,
    "name": "Excitation"
  },
  {
    "id": 1047025,
    "name": "The Blue Star"
  },
  {
    "id": 585129,
    "name": "Cine Gibi: O Filme"
  },
  {
    "id": 100095,
    "name": "Rosaura at 10 O'Clock"
  },
  {
    "id": 441475,
    "name": "Memoria"
  },
  {
    "id": 47783,
    "name": "Limite"
  },
  {
    "id": 80562,
    "name": "Neighboring Sounds"
  },
  {
    "id": 430476,
    "name": "Marighella"
  },
  {
    "id": 18240,
    "name": "Chronicle of a Boy Alone"
  },
  {
    "id": 104280,
    "name": "Memories of Prison"
  },
  {
    "id": 53574,
    "name": "Black God, White Devil"
  },
  {
    "id": 51316,
    "name": "Barren Lives"
  },
  {
    "id": 21729,
    "name": "Cinema, Aspirins and Vultures"
  },
  {
    "id": 23032,
    "name": "Hour of the Star"
  },
  {
    "id": 819859,
    "name": "Utama"
  },
  {
    "id": 265927,
    "name": "Land and Shade"
  },
  {
    "id": 915,
    "name": "Manuelita"
  },
  {
    "id": 145461,
    "name": "My Mom Is a Character"
  },
  {
    "id": 128212,
    "name": "Killed the Family and Went to the Movies"
  },
  {
    "id": 420726,
    "name": "Loveling"
  },
  {
    "id": 121538,
    "name": "Invasion"
  },
  {
    "id": 547510,
    "name": "My Mom Is a Character 3"
  },
  {
    "id": 21717,
    "name": "Roma"
  },
  {
    "id": 665212,
    "name": "My Brothers Dream Awake"
  },
  {
    "id": 38521,
    "name": "Four Days in September"
  },
  {
    "id": 591940,
    "name": "A Bruddah's Mind"
  },
  {
    "id": 22899,
    "name": "Bye Bye Brazil"
  },
  {
    "id": 13112,
    "name": "Undertow"
  },
  {
    "id": 111147,
    "name": "Golden Mouth"
  },
  {
    "id": 92163,
    "name": "Iracema"
  },
  {
    "id": 33010,
    "name": "The House of Sand"
  },
  {
    "id": 188393,
    "name": "Rodents"
  },
  {
    "id": 174321,
    "name": "Memoirs of a Strangler of Blondes"
  },
  {
    "id": 117528,
    "name": "Blood of the Condor"
  },
  {
    "id": 20764,
    "name": "The Holy Girl"
  },
  {
    "id": 247111,
    "name": "The Club"
  },
  {
    "id": 44777,
    "name": "The Journey"
  },
  {
    "id": 20224,
    "name": "The Paranoids"
  },
  {
    "id": 64181,
    "name": "Garotas do ABC"
  },
  {
    "id": 593801,
    "name": "Official Competition"
  },
  {
    "id": 60954,
    "name": "The Dark Side of the Heart"
  },
  {
    "id": 342762,
    "name": "The Distinguished Citizen"
  },
  {
    "id": 127129,
    "name": "Rio 2096: A Story of Love and Fury"
  },
  {
    "id": 45051,
    "name": "Kiss of the Spider Woman"
  },
  {
    "id": 834364,
    "name": "Aunt Virginia"
  },
  {
    "id": 10850,
    "name": "Night of the Pencils"
  },
  {
    "id": 24581,
    "name": "The City and the Dogs"
  },
  {
    "id": 362367,
    "name": "A Fantastic Woman"
  },
  {
    "id": 192304,
    "name": "Pajarito Gómez"
  },
  {
    "id": 27435,
    "name": "Whisky"
  },
  {
    "id": 31639,
    "name": "This Night I'll Possess Your Corpse"
  },
  {
    "id": 27610,
    "name": "The Dependent"
  },
  {
    "id": 34400,
    "name": "The Maid"
  },
  {
    "id": 30358,
    "name": "Common Ground"
  },
  {
    "id": 188889,
    "name": "Last Days of the Victim"
  },
  {
    "id": 1846,
    "name": "Rebellion in Patagonia"
  },
  {
    "id": 139971,
    "name": "The Dare"
  },
  {
    "id": 351219,
    "name": "Monos"
  },
  {
    "id": 268091,
    "name": "Heart and Guts"
  },
  {
    "id": 501950,
    "name": "In the Heart of the World"
  },
  {
    "id": 165840,
    "name": "Sea of Roses"
  },
  {
    "id": 18711,
    "name": "Romance"
  },
  {
    "id": 537324,
    "name": "Pacarrete"
  },
  {
    "id": 39133,
    "name": "Last Stop 174"
  },
  {
    "id": 100977,
    "name": "Paraguayan Hammock"
  },
  {
    "id": 15479,
    "name": "Cine Gibi 4: Meninos e Meninas"
  },
  {
    "id": 1063156,
    "name": "The Day I Met You"
  },
  {
    "id": 795895,
    "name": "She and I"
  },
  {
    "id": 83521,
    "name": "Found Memories"
  },
  {
    "id": 139875,
    "name": "The Man of The Sputnik"
  },
  {
    "id": 682867,
    "name": "The First Fallen"
  },
  {
    "id": 211863,
    "name": "The Men I Had"
  },
  {
    "id": 99773,
    "name": "7 Boxes"
  },
  {
    "id": 33496,
    "name": "The Milk of Sorrow"
  },
  {
    "id": 66366,
    "name": "The Clown"
  },
  {
    "id": 159269,
    "name": "The Traitors"
  },
  {
    "id": 22981,
    "name": "Camila"
  },
  {
    "id": 32256,
    "name": "Valentin"
  },
  {
    "id": 78511,
    "name": "La Libertad"
  },
  {
    "id": 43106,
    "name": "The Year My Parents Went on Vacation"
  },
  {
    "id": 448688,
    "name": "The Silences"
  },
  {
    "id": 784661,
    "name": "Charcoal"
  },
  {
    "id": 354766,
    "name": "The Beast Must Die"
  },
  {
    "id": 66892,
    "name": "Mango Yellow"
  },
  {
    "id": 43983,
    "name": "The Aerial"
  },
  {
    "id": 86599,
    "name": "Last Images of the Shipwreck"
  },
  {
    "id": 116821,
    "name": "Sweet Mother"
  },
  {
    "id": 747357,
    "name": "Bob Spit: We Do Not Like People"
  },
  {
    "id": 217479,
    "name": "De Onde Eu Te Vejo"
  },
  {
    "id": 8228,
    "name": "Moon of Avellaneda"
  },
  {
    "id": 20059,
    "name": "Stolen Dreams"
  },
  {
    "id": 23891,
    "name": "Garage Olimpo"
  },
  {
    "id": 47839,
    "name": "The Pope's Toilet"
  },
  {
    "id": 587770,
    "name": "The Siamese Bond"
  },
  {
    "id": 72792,
    "name": "Cine Gibi 3: Planos Infalíveis"
  },
  {
    "id": 99432,
    "name": "Nazareno Cruz and the Wolf"
  },
  {
    "id": 833440,
    "name": "Dry Ground Burning"
  },
  {
    "id": 104243,
    "name": "Fine Powder"
  },
  {
    "id": 61876,
    "name": "The Conspirators"
  },
  {
    "id": 577391,
    "name": "Pureza"
  },
  {
    "id": 464451,
    "name": "Long Way Home"
  },
  {
    "id": 510819,
    "name": "Song Without a Name"
  },
  {
    "id": 129921,
    "name": "Lucio Flavio"
  },
  {
    "id": 142941,
    "name": "The House of the Angel"
  },
  {
    "id": 167077,
    "name": "Cine Gibi 2"
  },
  {
    "id": 176549,
    "name": "The Black Vampire"
  },
  {
    "id": 662,
    "name": "The Turning Wind"
  },
  {
    "id": 22837,
    "name": "Dona Flor and Her Two Husbands"
  },
  {
    "id": 954512,
    "name": "Rotting in the Sun"
  },
  {
    "id": 122540,
    "name": "The Storytellers"
  },
  {
    "id": 34811,
    "name": "Burnt Money"
  },
  {
    "id": 43709,
    "name": "The Aura"
  },
  {
    "id": 30558,
    "name": "Wild Horses"
  },
  {
    "id": 13883,
    "name": "Brother"
  },
  {
    "id": 28065,
    "name": "Los Muertos"
  },
  {
    "id": 15649,
    "name": "Silvia Prieto"
  },
  {
    "id": 51659,
    "name": "Maria Full of Grace"
  }
]